pyembed_markdown-1.1.0-py2.7-nspkg.pth
pyembed/markdown/pattern.py
pyembed/markdown/__init__.py
pyembed_markdown-1.1.0.dist-info/metadata.json
pyembed_markdown-1.1.0.dist-info/top_level.txt
pyembed_markdown-1.1.0.dist-info/METADATA
pyembed_markdown-1.1.0.dist-info/RECORD
pyembed_markdown-1.1.0.dist-info/WHEEL
pyembed_markdown-1.1.0.dist-info/DESCRIPTION.rst
pyembed_markdown-1.1.0.dist-info/namespace_packages.txt
