Metadata-Version: 1.1
Name: pyembed-markdown
Version: 1.1.0
Summary: Python Markdown extension for embedding content using OEmbed
Home-page: http://pyembed.github.io
Author: Matt Thomson
Author-email: mattjohnthomson@gmail.com
License: Copyright (c) 2013 Matt Thomson
